pydantic_base_aiogram/__init__.py
pydantic_base_aiogram/abstract_handler.py
pydantic_base_aiogram/controller/__init__.py
pydantic_base_aiogram/controller/abstract.py
pydantic_base_aiogram/controller/base.py
pydantic_base_aiogram/controller/bool.py
pydantic_base_aiogram/controller/cq_checkbox/__init__.py
pydantic_base_aiogram/controller/cq_checkbox/base.py
pydantic_base_aiogram/controller/cq_checkbox/main.py
pydantic_base_aiogram/controller/cq_checkbox/multiple.py
pydantic_base_aiogram/controller/cq_checkbox/single.py
pydantic_base_aiogram/controller/custom_data_str/__init__.py
pydantic_base_aiogram/controller/custom_data_str/base.py
pydantic_base_aiogram/controller/custom_data_str/main.py
pydantic_base_aiogram/controller/custom_data_str/multiple.py
pydantic_base_aiogram/controller/custom_data_str/single.py
pydantic_base_aiogram/controller/date_message_text.py
pydantic_base_aiogram/controller/factory.py
pydantic_base_aiogram/controller/file.py
pydantic_base_aiogram/controller/optional_file.py
pydantic_base_aiogram/controller/type_base_message_text.py
pydantic_base_aiogram/dialecsts.py
pydantic_base_aiogram/dynamic/README.md
pydantic_base_aiogram/dynamic/__init__.py
pydantic_base_aiogram/dynamic/builder.py
pydantic_base_aiogram/dynamic/field_metadata.py
pydantic_base_aiogram/dynamic_factory/README.md
pydantic_base_aiogram/dynamic_factory/__init__.py
pydantic_base_aiogram/dynamic_factory/enums.py
pydantic_base_aiogram/dynamic_factory/handler.py
pydantic_base_aiogram/dynamic_factory/schema.py
pydantic_base_aiogram/exceptions.py
pydantic_base_aiogram/field_factory/__init__.py
pydantic_base_aiogram/field_factory/base.py
pydantic_base_aiogram/field_factory/enum.py
pydantic_base_aiogram/field_factory/main.py
pydantic_base_aiogram/field_factory/model.py
pydantic_base_aiogram/field_factory/mult_single_splitter.py
pydantic_base_aiogram/field_factory/union.py
pydantic_base_aiogram/main.py
pydantic_base_aiogram/state_builder.py
pydantic_base_aiogram/types.py
pydantic_base_aiogram-1.0.165.dist-info/METADATA
pydantic_base_aiogram-1.0.165.dist-info/WHEEL
pydantic_base_aiogram-1.0.165.dist-info/RECORD
