Metadata-Version: 2.1
Name: pydantic-base-aiogram
Version: 1.0.165
Summary: This code simplifies the conversion of Pydantic schemas into Aiogram handler groups, making it easy to create form-filling handlers.
Author: axdjuraev
Author-email: axdjuraev@gmail.com
Requires-Python: >=3.10,<4.0
Classifier: Programming Language :: Python :: 3
Classifier: Programming Language :: Python :: 3.10
Classifier: Programming Language :: Python :: 3.11
Classifier: Programming Language :: Python :: 3.12
Requires-Dist: aiogram (==3.0.0b7)
Requires-Dist: axabc (>=0.0.62,<0.0.63)
Requires-Dist: pydantic (==1.10.4)
